q2netcdf/QConfig.py
q2netcdf/QData.py
q2netcdf/QFile.py
q2netcdf/QHeader.py
q2netcdf/QHexCodes.py
q2netcdf/QRecordType.py
q2netcdf/QReduce.py
q2netcdf/QVersion.py
q2netcdf/__init__.py
q2netcdf/mergeqfiles.cfg
q2netcdf/mergeqfiles.py
q2netcdf/mkISDPcfg.py
q2netcdf/q2netcdf.py
q2netcdf-0.4.0.dist-info/METADATA
q2netcdf-0.4.0.dist-info/WHEEL
q2netcdf-0.4.0.dist-info/entry_points.txt
q2netcdf-0.4.0.dist-info/licenses/LICENSE
q2netcdf-0.4.0.dist-info/RECORD
