Metadata-Version: 2.4
Name: q2netcdf
Version: 0.4.0
Summary: Manipulate Rockland Scientific's Q-files
Project-URL: Repository, https://github.com/mousebrains/q2netcdf
Author-email: Pat Welch <pat@mousebrains.com>
Maintainer-email: Pat Welch <pat@mousebrains.com>
License-Expression: GPL-3.0-or-later
License-File: LICENSE
Keywords: ISDP,MicroRider,Q-file,Rockland
Classifier: Development Status :: 4 - Beta
Classifier: Intended Audience :: Science/Research
Classifier: Programming Language :: Python :: 3
Classifier: Topic :: Scientific/Engineering :: Oceanography
Requires-Python: >=3.10
Requires-Dist: netcdf4>=1.5.3
Requires-Dist: numpy>=1.17.0
Requires-Dist: pyyaml>=5.1
Requires-Dist: xarray>=0.16.0
Provides-Extra: dev
Requires-Dist: bandit[toml]>=1.7; extra == 'dev'
Requires-Dist: mypy>=1.0; extra == 'dev'
Requires-Dist: pre-commit>=3.0; extra == 'dev'
Requires-Dist: pytest-cov>=4.0; extra == 'dev'
Requires-Dist: pytest>=7.0; extra == 'dev'
Requires-Dist: ruff>=0.1.0; extra == 'dev'
